vsparsedvd/IsoFile.py
vsparsedvd/IsoFileCore.py
vsparsedvd/__init__.py
vsparsedvd/_metadata.py
vsparsedvd/dataclasses.py
vsparsedvd/py.typed
vsparsedvd/DVDIndexers/D2VWitch.py
vsparsedvd/DVDIndexers/DGIndex.py
vsparsedvd/DVDIndexers/DGIndexNV.py
vsparsedvd/DVDIndexers/DVDIndexer.py
vsparsedvd/DVDIndexers/__init__.py
vsparsedvd/utils/__init__.py
vsparsedvd/utils/spathlib.py
vsparsedvd/utils/types.py
vsparsedvd/utils/utils.py
vsparsedvd-0.1.0.dist-info/LICENSE
vsparsedvd-0.1.0.dist-info/METADATA
vsparsedvd-0.1.0.dist-info/WHEEL
vsparsedvd-0.1.0.dist-info/top_level.txt
vsparsedvd-0.1.0.dist-info/RECORD
