Metadata-Version: 2.1
Name: vsparsedvd
Version: 0.1.0
Summary: Vapoursynth Wrapper for DVDs stuff
Author: Setsugen no ao
Author-email: setsugen@setsugen.dev
Maintainer: Setsugen no ao
Maintainer-email: setsugen@setsugen.dev
Project-URL: Source Code, https://github.com/Irrational-Encoding-Wizardry/vs-parsedvd
Project-URL: Documentation, https://vsparsedvd.encode.moe/en/latest/
Project-URL: Contact, https://discord.gg/qxTxVJGtst
Classifier: Programming Language :: Python :: 3
Classifier: License :: OSI Approved :: MIT License
Classifier: Operating System :: OS Independent
Requires-Python: >=3.10
License-File: LICENSE
Requires-Dist: VapourSynth (>=59)
Requires-Dist: pyparsedvd (>=0.0.3)
